flushai/__init__.py
flushai/basemodel.py
flushai/text2imgbase.py
flushai/txt2gifbase.py
flushai/chains/__init__.py
flushai/chains/chain.py
flushai/exceptions/__init__.py
flushai/exceptions/chain_error.py
flushai/gallery/__init__.py
flushai/gallery/image_gallery.py
flushai/loaders/__init__.py
flushai/loaders/base_loader.py
flushai/loaders/images/__init__.py
flushai/loaders/images/dbx.py
flushai/loaders/images/directory.py
flushai/loaders/images/google_drive.py
flushai/loaders/images/laion.py
flushai/loaders/images/pexels.py
flushai/loaders/images/pixabay.py
flushai/loaders/images/serpapi.py
flushai/loaders/images/youtube_splitter.py
flushai/loaders/text/__init__.py
flushai/loaders/text/pdf_loader.py
flushai/models/__init__.py
flushai/models/basemodel.py
flushai/models/diffusion/__init__.py
flushai/models/diffusion/img2img/__init__.py
flushai/models/diffusion/img2img/absolute_reality.py
flushai/models/diffusion/img2img/anything_v5.py
flushai/models/diffusion/img2img/img2imgbase.py
flushai/models/diffusion/img2img/openjourney_v4.py
flushai/models/diffusion/img2img/realistic_vision_v51.py
flushai/models/diffusion/img2img/stable_diffusion_v15.py
flushai/models/diffusion/img2img/stable_diffusion_v21.py
flushai/models/diffusion/img2img/stable_diffusion_xl.py
flushai/models/diffusion/img2img/upscalers/__init__.py
flushai/models/diffusion/img2img/upscalers/real_esrgan.py
flushai/models/diffusion/text2img/__init__.py
flushai/models/diffusion/text2img/absolute_reality.py
flushai/models/diffusion/text2img/anything_v5.py
flushai/models/diffusion/text2img/dalle.py
flushai/models/diffusion/text2img/openjourney_v4.py
flushai/models/diffusion/text2img/realistic_vision_v51.py
flushai/models/diffusion/text2img/stable_diffusion_v15.py
flushai/models/diffusion/text2img/stable_diffusion_v21.py
flushai/models/diffusion/text2img/stable_diffusion_xl.py
flushai/models/diffusion/text2img/text2imgbase.py
flushai/models/llms/__init__.py
flushai/models/llms/openai.py
flushai/prompts/__init__.py
flushai-1.0.5.dist-info/LICENCE
flushai-1.0.5.dist-info/METADATA
flushai-1.0.5.dist-info/WHEEL
flushai-1.0.5.dist-info/top_level.txt
flushai-1.0.5.dist-info/RECORD
